README.md
setup.py
PipeTransformer.egg-info/PKG-INFO
PipeTransformer.egg-info/SOURCES.txt
PipeTransformer.egg-info/dependency_links.txt
PipeTransformer.egg-info/top_level.txt
PipelineTransformer/PipeTransformer.py
PipelineTransformer/__init__.py