Metadata-Version: 2.1
Name: PipeTransformer
Version: 0.0.1
Summary: customerized pipeline transformer
Home-page: UNKNOWN
Author: zuel_quant_lab
Author-email: 2285198670@qq.com
License: UNKNOWN
Platform: UNKNOWN
Classifier: Programming Language :: Python :: 3
Classifier: License :: OSI Approved :: MIT License
Classifier: Operating System :: OS Independent
Requires-Python: >=3.6
